falwa/__init__.py
falwa/barotropic_field.py
falwa/basis.py
falwa/compute_flux_dirinv.cpython-310-darwin.so
falwa/compute_lwa_and_barotropic_fluxes.cpython-310-darwin.so
falwa/compute_lwa_only_nhn22.cpython-310-darwin.so
falwa/compute_qgpv.cpython-310-darwin.so
falwa/compute_qgpv_direct_inv.cpython-310-darwin.so
falwa/compute_qref_and_fawa_first.cpython-310-darwin.so
falwa/compute_reference_states.cpython-310-darwin.so
falwa/constant.py
falwa/data_storage.py
falwa/matrix_after_inversion.cpython-310-darwin.so
falwa/matrix_b4_inversion.cpython-310-darwin.so
falwa/netcdf_utils.py
falwa/oopinterface.py
falwa/plot_utils.py
falwa/preprocessing.py
falwa/stat_utils.py
falwa/upward_sweep.cpython-310-darwin.so
falwa/utilities.py
falwa/wrapper.py
falwa/xarrayinterface.py
falwa/legacy/__init__.py
falwa/legacy/beta_version.py
tests/__init__.py
tests/conftest.py
tests/test_barotropic_field.py
tests/test_basis.py
tests/test_oopinterface.py
tests/test_output_results.py
tests/test_utilities.py
tests/test_xarrayinterface.py
falwa-1.3.0.dist-info/LICENSE.txt
falwa-1.3.0.dist-info/METADATA
falwa-1.3.0.dist-info/WHEEL
falwa-1.3.0.dist-info/top_level.txt
falwa-1.3.0.dist-info/RECORD
