Metadata-Version: 2.1
Name: falwa
Version: 1.3.0
Summary: python package to compute finite-amplitude local wave activity (Huang and Nakamura 2016, JAS)
Home-page: https://github.com/csyhuang/hn2016_falwa
Author: Clare S. Y. Huang
Author-email: csyhuang@uchicago.edu
License: MIT
Requires-Python: >=3
License-File: LICENSE.txt
Requires-Dist: numpy
Requires-Dist: scipy
Requires-Dist: xarray
